MANIFEST.in
README.md
setup.py
dash/__init__.py
dash/authentication.py
dash/dash.py
dash/dependencies.py
dash/exceptions.py
dash/plotly_api.py
dash/resources.py
dash/version.py
dash.ly.egg-info/PKG-INFO
dash.ly.egg-info/SOURCES.txt
dash.ly.egg-info/dependency_links.txt
dash.ly.egg-info/requires.txt
dash.ly.egg-info/top_level.txt
dash/development/__init__.py
dash/development/base_component.py
dash/development/component_loader.py