Metadata-Version: 1.0
Name: dash.ly
Version: 0.15.2
Summary: UNKNOWN
Home-page: UNKNOWN
Author: chris p
Author-email: chris@plot.ly
License: MIT
Platform: UNKNOWN
